yapitest/Development.md
yapitest/__init__.py
yapitest/main.py
yapitest/find/__init__.py
yapitest/find/finder.py
yapitest/test/.gitignore
yapitest/test/__init__.py
yapitest/test/config.py
yapitest/test/file.py
yapitest/test/step.py
yapitest/test/test.py
yapitest/test/assertions/assertion.py
yapitest/test/assertions/body_assertion.py
yapitest/test/assertions/full_assertion.py
yapitest/test/assertions/status_code_assertion.py
yapitest/utils/__init__.py
yapitest/utils/console.py
yapitest/utils/dict_wrapper.py
yapitest/utils/exc.py
yapitest/utils/paths.py
yapitest/utils/random.py
yapitest/utils/time.py
yapitest/utils/yaml.py
yapitest-0.0.5.dist-info/entry_points.txt
yapitest-0.0.5.dist-info/LICENSE
yapitest-0.0.5.dist-info/WHEEL
yapitest-0.0.5.dist-info/METADATA
yapitest-0.0.5.dist-info/RECORD
