Metadata-Version: 2.1
Name: yapitest
Version: 0.0.5
Summary: Yaml based API testing framework
Author-email: Charlie Dudzik <dudzikc@outlook.com>
Classifier: License :: OSI Approved :: MIT License
Requires-Dist: ruamel.yaml
